ament_cmake_libraries/_dummy.cpython-313-x86_64-linux-gnu.so
ros_ament_cmake_libraries-2.7.3.data/data/share/ament_cmake_libraries/local_setup.bash
ros_ament_cmake_libraries-2.7.3.data/data/share/ament_cmake_libraries/local_setup.dsv
ros_ament_cmake_libraries-2.7.3.data/data/share/ament_cmake_libraries/local_setup.sh
ros_ament_cmake_libraries-2.7.3.data/data/share/ament_cmake_libraries/local_setup.zsh
ros_ament_cmake_libraries-2.7.3.data/data/share/ament_cmake_libraries/package.dsv
ros_ament_cmake_libraries-2.7.3.data/data/share/ament_cmake_libraries/package.xml
ros_ament_cmake_libraries-2.7.3.data/data/share/ament_cmake_libraries/cmake/ament_cmake_libraries-extras.cmake
ros_ament_cmake_libraries-2.7.3.data/data/share/ament_cmake_libraries/cmake/ament_cmake_librariesConfig-version.cmake
ros_ament_cmake_libraries-2.7.3.data/data/share/ament_cmake_libraries/cmake/ament_cmake_librariesConfig.cmake
ros_ament_cmake_libraries-2.7.3.data/data/share/ament_cmake_libraries/cmake/ament_libraries_deduplicate.cmake
ros_ament_cmake_libraries-2.7.3.data/data/share/ament_cmake_libraries/environment/ament_prefix_path.dsv
ros_ament_cmake_libraries-2.7.3.data/data/share/ament_cmake_libraries/environment/ament_prefix_path.sh
ros_ament_cmake_libraries-2.7.3.data/data/share/ament_cmake_libraries/environment/path.dsv
ros_ament_cmake_libraries-2.7.3.data/data/share/ament_cmake_libraries/environment/path.sh
ros_ament_cmake_libraries-2.7.3.data/data/share/ament_index/resource_index/package_run_dependencies/ament_cmake_libraries
ros_ament_cmake_libraries-2.7.3.data/data/share/ament_index/resource_index/packages/ament_cmake_libraries
ros_ament_cmake_libraries-2.7.3.data/data/share/ament_index/resource_index/parent_prefix_path/ament_cmake_libraries
ros_ament_cmake_libraries-2.7.3.dist-info/METADATA
ros_ament_cmake_libraries-2.7.3.dist-info/WHEEL
ros_ament_cmake_libraries-2.7.3.dist-info/top_level.txt
ros_ament_cmake_libraries-2.7.3.dist-info/RECORD
